sheikh_package100/__init__.py
sheikhmultiplcation100-0.0.1.dist-info/LICENSE.txt
sheikhmultiplcation100-0.0.1.dist-info/METADATA
sheikhmultiplcation100-0.0.1.dist-info/WHEEL
sheikhmultiplcation100-0.0.1.dist-info/top_level.txt
sheikhmultiplcation100-0.0.1.dist-info/RECORD
