Metadata-Version: 2.1
Name: sheikhmultiplcation100
Version: 0.0.1
Summary: This is a simple package for learning purpose
Home-page: UNKNOWN
Author: Sheikh Faizan
Author-email: fzsaleem786@gmail.com
License: UNKNOWN
Platform: UNKNOWN
Classifier: Programming Language :: Python :: 3
Classifier: License :: OSI Approved :: MIT License
Classifier: Operating System :: OS Independent
License-File: LICENSE.txt
